[
    {
        "ano": 2026,
        "mes": 3,
        "tipoDespesa": "PASSAGEM AÉREA - SIGEPA",
        "codDocumento": "5446D1D3-7AB1-4D98-8E46-E6EA11917FE7",
        "tipoDocumento": "Nota Fiscal",
        "codTipoDocumento": 0,
        "dataDocumento": "2026-03-17T00:00:00",
        "numDocumento": "GQ4Q5H",
        "valorDocumento": 1486.9,
        "urlDocumento": null,
        "nomeFornecedor": "Azul Linhas Aéreas",
        "cnpjCpfFornecedor": "",
        "valorLiquido": 1486.9,
        "valorGlosa": 0.0,
        "numRessarcimento": "0",
        "codLote": 0,
        "parcela": 0
    },
    {
        "ano": 2026,
        "mes": 3,
        "tipoDespesa": "PASSAGEM AÉREA - SIGEPA",
        "codDocumento": "727C2169-EF49-4B76-9D96-DEF74DBD354C",
        "tipoDocumento": "Nota Fiscal",
        "codTipoDocumento": 0,
        "dataDocumento": "2026-03-05T00:00:00",
        "numDocumento": "IRMV6R",
        "valorDocumento": 375.01,
        "urlDocumento": null,
        "nomeFornecedor": "Azul Linhas Aéreas",
        "cnpjCpfFornecedor": "",
        "valorLiquido": 375.01,
        "valorGlosa": 0.0,
        "numRessarcimento": "0",
        "codLote": 0,
        "parcela": 0
    },
    {
        "ano": 2026,
        "mes": 3,
        "tipoDespesa": "PASSAGEM AÉREA - SIGEPA",
        "codDocumento": "5D48A82D-1206-4447-943E-9F3F9DE45AE9",
        "tipoDocumento": "Nota Fiscal",
        "codTipoDocumento": 0,
        "dataDocumento": "2026-03-05T00:00:00",
        "numDocumento": "KSE8KR",
        "valorDocumento": 459.61,
        "urlDocumento": null,
        "nomeFornecedor": "Azul Linhas Aéreas",
        "cnpjCpfFornecedor": "",
        "valorLiquido": 459.61,
        "valorGlosa": 0.0,
        "numRessarcimento": "0",
        "codLote": 0,
        "parcela": 0
    },
    {
        "ano": 2026,
        "mes": 1,
        "tipoDespesa": "PASSAGEM AÉREA - SIGEPA",
        "codDocumento": "6BD82F77-D8F9-4A60-AF9D-91E7E55EAFC2",
        "tipoDocumento": "Nota Fiscal",
        "codTipoDocumento": 0,
        "dataDocumento": "2026-01-29T00:00:00",
        "numDocumento": "LEN8XB",
        "valorDocumento": 316.93,
        "urlDocumento": null,
        "nomeFornecedor": "Azul Linhas Aéreas",
        "cnpjCpfFornecedor": "",
        "valorLiquido": 316.93,
        "valorGlosa": 0.0,
        "numRessarcimento": "0",
        "codLote": 0,
        "parcela": 0
    },
    {
        "ano": 2026,
        "mes": 1,
        "tipoDespesa": "PASSAGEM AÉREA - SIGEPA",
        "codDocumento": "3196B9BF-57B9-4488-80E7-584FD77CE9DB",
        "tipoDocumento": "Nota Fiscal",
        "codTipoDocumento": 0,
        "dataDocumento": "2026-01-29T00:00:00",
        "numDocumento": "LN9NKD",
        "valorDocumento": 316.93,
        "urlDocumento": null,
        "nomeFornecedor": "Azul Linhas Aéreas",
        "cnpjCpfFornecedor": "",
        "valorLiquido": 316.93,
        "valorGlosa": 0.0,
        "numRessarcimento": "0",
        "codLote": 0,
        "parcela": 0
    },
    {
        "ano": 2026,
        "mes": 4,
        "tipoDespesa": "PASSAGEM AÉREA - SIGEPA",
        "codDocumento": "34727B3A-8FE0-45C0-8791-398BDDAFEAA5",
        "tipoDocumento": "Nota Fiscal",
        "codTipoDocumento": 0,
        "dataDocumento": "2026-04-15T00:00:00",
        "numDocumento": "MSGC7B",
        "valorDocumento": 706.71,
        "urlDocumento": null,
        "nomeFornecedor": "Azul Linhas Aéreas",
        "cnpjCpfFornecedor": "",
        "valorLiquido": 706.71,
        "valorGlosa": 0.0,
        "numRessarcimento": "0",
        "codLote": 0,
        "parcela": 0
    },
    {
        "ano": 2026,
        "mes": 2,
        "tipoDespesa": "PASSAGEM AÉREA - SIGEPA",
        "codDocumento": "FB549BC6-17CC-43B8-9C78-F7E3CE4A9DF1",
        "tipoDocumento": "Nota Fiscal",
        "codTipoDocumento": 0,
        "dataDocumento": "2026-02-11T00:00:00",
        "numDocumento": "NRV7HE",
        "valorDocumento": 657.41,
        "urlDocumento": null,
        "nomeFornecedor": "Azul Linhas Aéreas",
        "cnpjCpfFornecedor": "",
        "valorLiquido": 657.41,
        "valorGlosa": 0.0,
        "numRessarcimento": "0",
        "codLote": 0,
        "parcela": 0
    },
    {
        "ano": 2026,
        "mes": 3,
        "tipoDespesa": "PASSAGEM AÉREA - SIGEPA",
        "codDocumento": "3013E464-5BE3-4785-9704-A07E132E59FD",
        "tipoDocumento": "Nota Fiscal",
        "codTipoDocumento": 0,
        "dataDocumento": "2026-03-05T00:00:00",
        "numDocumento": "NRZJHH",
        "valorDocumento": 374.08,
        "urlDocumento": null,
        "nomeFornecedor": "Azul Linhas Aéreas",
        "cnpjCpfFornecedor": "",
        "valorLiquido": 374.08,
        "valorGlosa": 0.0,
        "numRessarcimento": "0",
        "codLote": 0,
        "parcela": 0
    },
    {
        "ano": 2026,
        "mes": 1,
        "tipoDespesa": "PASSAGEM AÉREA - SIGEPA",
        "codDocumento": "B15DC3FC-D7AA-4098-971E-48F8C0315EB3",
        "tipoDocumento": "Nota Fiscal",
        "codTipoDocumento": 0,
        "dataDocumento": "2026-01-29T00:00:00",
        "numDocumento": "PLV7KW",
        "valorDocumento": 324.74,
        "urlDocumento": null,
        "nomeFornecedor": "Azul Linhas Aéreas",
        "cnpjCpfFornecedor": "",
        "valorLiquido": 324.74,
        "valorGlosa": 0.0,
        "numRessarcimento": "0",
        "codLote": 0,
        "parcela": 0
    },
    {
        "ano": 2026,
        "mes": 3,
        "tipoDespesa": "PASSAGEM AÉREA - SIGEPA",
        "codDocumento": "8EE88B83-E113-4D7C-BE48-3F798784FFCA",
        "tipoDocumento": "Nota Fiscal",
        "codTipoDocumento": 0,
        "dataDocumento": "2026-03-05T00:00:00",
        "numDocumento": "SH7CWY",
        "valorDocumento": 228.71,
        "urlDocumento": null,
        "nomeFornecedor": "Azul Linhas Aéreas",
        "cnpjCpfFornecedor": "",
        "valorLiquido": 228.71,
        "valorGlosa": 0.0,
        "numRessarcimento": "0",
        "codLote": 0,
        "parcela": 0
    },
    {
        "ano": 2026,
        "mes": 1,
        "tipoDespesa": "PASSAGEM AÉREA - SIGEPA",
        "codDocumento": "6A78502C-B09C-4BEC-AA1D-04E4742D98EA",
        "tipoDocumento": "Nota Fiscal",
        "codTipoDocumento": 0,
        "dataDocumento": "2026-01-29T00:00:00",
        "numDocumento": "TQMJTK",
        "valorDocumento": 381.0,
        "urlDocumento": null,
        "nomeFornecedor": "Azul Linhas Aéreas",
        "cnpjCpfFornecedor": "",
        "valorLiquido": 381.0,
        "valorGlosa": 0.0,
        "numRessarcimento": "0",
        "codLote": 0,
        "parcela": 0
    },
    {
        "ano": 2026,
        "mes": 2,
        "tipoDespesa": "PASSAGEM AÉREA - SIGEPA",
        "codDocumento": "93E9CE5B-563F-4B0C-A6E6-F2FEA1EBBD17",
        "tipoDocumento": "Nota Fiscal",
        "codTipoDocumento": 0,
        "dataDocumento": "2026-02-11T00:00:00",
        "numDocumento": "URKUSH",
        "valorDocumento": 682.34,
        "urlDocumento": null,
        "nomeFornecedor": "Azul Linhas Aéreas",
        "cnpjCpfFornecedor": "",
        "valorLiquido": 682.34,
        "valorGlosa": 0.0,
        "numRessarcimento": "0",
        "codLote": 0,
        "parcela": 0
    },
    {
        "ano": 2026,
        "mes": 3,
        "tipoDespesa": "PASSAGEM AÉREA - SIGEPA",
        "codDocumento": "2853010E-435E-406C-9BDB-0F4088708A57",
        "tipoDocumento": "Nota Fiscal",
        "codTipoDocumento": 0,
        "dataDocumento": "2026-03-05T00:00:00",
        "numDocumento": "XRIDKH",
        "valorDocumento": 228.71,
        "urlDocumento": null,
        "nomeFornecedor": "Azul Linhas Aéreas",
        "cnpjCpfFornecedor": "",
        "valorLiquido": 228.71,
        "valorGlosa": 0.0,
        "numRessarcimento": "0",
        "codLote": 0,
        "parcela": 0
    },
    {
        "ano": 2026,
        "mes": 3,
        "tipoDespesa": "PASSAGEM AÉREA - SIGEPA",
        "codDocumento": "7E3FD53E-B2E0-4A39-9179-E6E66A4CE162",
        "tipoDocumento": "Nota Fiscal",
        "codTipoDocumento": 0,
        "dataDocumento": "2026-03-05T00:00:00",
        "numDocumento": "ZPS2TA",
        "valorDocumento": 227.78,
        "urlDocumento": null,
        "nomeFornecedor": "Azul Linhas Aéreas",
        "cnpjCpfFornecedor": "",
        "valorLiquido": 227.78,
        "valorGlosa": 0.0,
        "numRessarcimento": "0",
        "codLote": 0,
        "parcela": 0
    },
    {
        "ano": 2026,
        "mes": 4,
        "tipoDespesa": "PASSAGEM AÉREA - SIGEPA",
        "codDocumento": "F04D7BC4-209A-447B-A8C7-7AFFA4C97DF6",
        "tipoDocumento": "Nota Fiscal",
        "codTipoDocumento": 0,
        "dataDocumento": "2026-04-16T00:00:00",
        "numDocumento": "ZPS2TA",
        "valorDocumento": 1031.11,
        "urlDocumento": null,
        "nomeFornecedor": "Azul Linhas Aéreas",
        "cnpjCpfFornecedor": "",
        "valorLiquido": 1031.11,
        "valorGlosa": 0.0,
        "numRessarcimento": "0",
        "codLote": 0,
        "parcela": 0
    }
]