[
    {
        "ano": 2026,
        "mes": 4,
        "tipoDespesa": "PASSAGEM AÉREA - SIGEPA",
        "codDocumento": "BE5264A6-4124-4E78-9DED-7176AD0D066E",
        "tipoDocumento": "Nota Fiscal",
        "codTipoDocumento": 0,
        "dataDocumento": "2026-04-13T00:00:00",
        "numDocumento": "1272301423053",
        "valorDocumento": -620.17,
        "urlDocumento": null,
        "nomeFornecedor": "Gol Linhas Aéreas",
        "cnpjCpfFornecedor": "",
        "valorLiquido": -620.17,
        "valorGlosa": 0.0,
        "numRessarcimento": "0",
        "codLote": 0,
        "parcela": 0
    },
    {
        "ano": 2026,
        "mes": 1,
        "tipoDespesa": "PASSAGEM AÉREA - SIGEPA",
        "codDocumento": "1CD79A72-0ED5-49BF-BE4F-C70D216B5461",
        "tipoDocumento": "Nota Fiscal",
        "codTipoDocumento": 0,
        "dataDocumento": "2026-01-21T00:00:00",
        "numDocumento": "9572270145360",
        "valorDocumento": 3019.01,
        "urlDocumento": null,
        "nomeFornecedor": "LATAM Airlines Brasil",
        "cnpjCpfFornecedor": "",
        "valorLiquido": 3019.01,
        "valorGlosa": 0.0,
        "numRessarcimento": "0",
        "codLote": 0,
        "parcela": 0
    },
    {
        "ano": 2026,
        "mes": 2,
        "tipoDespesa": "PASSAGEM AÉREA - SIGEPA",
        "codDocumento": "08CD91B5-B2FF-40C7-9F1F-AB40C112727C",
        "tipoDocumento": "Nota Fiscal",
        "codTipoDocumento": 0,
        "dataDocumento": "2026-02-03T00:00:00",
        "numDocumento": "9572271932286",
        "valorDocumento": -1662.9,
        "urlDocumento": null,
        "nomeFornecedor": "LATAM Airlines Brasil",
        "cnpjCpfFornecedor": "",
        "valorLiquido": -1662.9,
        "valorGlosa": 0.0,
        "numRessarcimento": "0",
        "codLote": 0,
        "parcela": 0
    },
    {
        "ano": 2026,
        "mes": 2,
        "tipoDespesa": "PASSAGEM AÉREA - SIGEPA",
        "codDocumento": "08CD91B5-B2FF-40C7-9F1F-AB40C112727C",
        "tipoDocumento": "Nota Fiscal",
        "codTipoDocumento": 0,
        "dataDocumento": "2026-02-03T00:00:00",
        "numDocumento": "9572271932286",
        "valorDocumento": 1662.9,
        "urlDocumento": null,
        "nomeFornecedor": "LATAM Airlines Brasil",
        "cnpjCpfFornecedor": "",
        "valorLiquido": 1662.9,
        "valorGlosa": 0.0,
        "numRessarcimento": "0",
        "codLote": 0,
        "parcela": 0
    },
    {
        "ano": 2026,
        "mes": 2,
        "tipoDespesa": "PASSAGEM AÉREA - SIGEPA",
        "codDocumento": "F6B31404-7466-40E5-989D-2B9E1F8AA570",
        "tipoDocumento": "Nota Fiscal",
        "codTipoDocumento": 0,
        "dataDocumento": "2026-02-07T00:00:00",
        "numDocumento": "9572272639940",
        "valorDocumento": 2144.3,
        "urlDocumento": null,
        "nomeFornecedor": "LATAM Airlines Brasil",
        "cnpjCpfFornecedor": "",
        "valorLiquido": 2144.3,
        "valorGlosa": 0.0,
        "numRessarcimento": "0",
        "codLote": 0,
        "parcela": 0
    },
    {
        "ano": 2026,
        "mes": 2,
        "tipoDespesa": "PASSAGEM AÉREA - SIGEPA",
        "codDocumento": "073B9299-3923-4612-B600-C99350C90BBD",
        "tipoDocumento": "Nota Fiscal",
        "codTipoDocumento": 0,
        "dataDocumento": "2026-02-07T00:00:00",
        "numDocumento": "9572272640506",
        "valorDocumento": -2393.19,
        "urlDocumento": null,
        "nomeFornecedor": "LATAM Airlines Brasil",
        "cnpjCpfFornecedor": "",
        "valorLiquido": -2393.19,
        "valorGlosa": 0.0,
        "numRessarcimento": "0",
        "codLote": 0,
        "parcela": 0
    },
    {
        "ano": 2026,
        "mes": 2,
        "tipoDespesa": "PASSAGEM AÉREA - SIGEPA",
        "codDocumento": "073B9299-3923-4612-B600-C99350C90BBD",
        "tipoDocumento": "Nota Fiscal",
        "codTipoDocumento": 0,
        "dataDocumento": "2026-02-07T00:00:00",
        "numDocumento": "9572272640506",
        "valorDocumento": 2393.19,
        "urlDocumento": null,
        "nomeFornecedor": "LATAM Airlines Brasil",
        "cnpjCpfFornecedor": "",
        "valorLiquido": 2393.19,
        "valorGlosa": 0.0,
        "numRessarcimento": "0",
        "codLote": 0,
        "parcela": 0
    },
    {
        "ano": 2026,
        "mes": 2,
        "tipoDespesa": "PASSAGEM AÉREA - SIGEPA",
        "codDocumento": "40A348FD-B218-4527-A9F4-EDBA398B188C",
        "tipoDocumento": "Nota Fiscal",
        "codTipoDocumento": 0,
        "dataDocumento": "2026-02-07T00:00:00",
        "numDocumento": "9572272641955",
        "valorDocumento": -1907.75,
        "urlDocumento": null,
        "nomeFornecedor": "LATAM Airlines Brasil",
        "cnpjCpfFornecedor": "",
        "valorLiquido": -1907.75,
        "valorGlosa": 0.0,
        "numRessarcimento": "0",
        "codLote": 0,
        "parcela": 0
    },
    {
        "ano": 2026,
        "mes": 2,
        "tipoDespesa": "PASSAGEM AÉREA - SIGEPA",
        "codDocumento": "40A348FD-B218-4527-A9F4-EDBA398B188C",
        "tipoDocumento": "Nota Fiscal",
        "codTipoDocumento": 0,
        "dataDocumento": "2026-02-07T00:00:00",
        "numDocumento": "9572272641955",
        "valorDocumento": -94.0,
        "urlDocumento": null,
        "nomeFornecedor": "LATAM Airlines Brasil",
        "cnpjCpfFornecedor": "",
        "valorLiquido": -94.0,
        "valorGlosa": 0.0,
        "numRessarcimento": "0",
        "codLote": 0,
        "parcela": 0
    },
    {
        "ano": 2026,
        "mes": 2,
        "tipoDespesa": "PASSAGEM AÉREA - SIGEPA",
        "codDocumento": "40A348FD-B218-4527-A9F4-EDBA398B188C",
        "tipoDocumento": "Nota Fiscal",
        "codTipoDocumento": 0,
        "dataDocumento": "2026-02-07T00:00:00",
        "numDocumento": "9572272641955",
        "valorDocumento": 94.0,
        "urlDocumento": null,
        "nomeFornecedor": "LATAM Airlines Brasil",
        "cnpjCpfFornecedor": "",
        "valorLiquido": 94.0,
        "valorGlosa": 0.0,
        "numRessarcimento": "0",
        "codLote": 0,
        "parcela": 0
    },
    {
        "ano": 2026,
        "mes": 2,
        "tipoDespesa": "PASSAGEM AÉREA - SIGEPA",
        "codDocumento": "40A348FD-B218-4527-A9F4-EDBA398B188C",
        "tipoDocumento": "Nota Fiscal",
        "codTipoDocumento": 0,
        "dataDocumento": "2026-02-07T00:00:00",
        "numDocumento": "9572272641955",
        "valorDocumento": 1907.75,
        "urlDocumento": null,
        "nomeFornecedor": "LATAM Airlines Brasil",
        "cnpjCpfFornecedor": "",
        "valorLiquido": 1907.75,
        "valorGlosa": 0.0,
        "numRessarcimento": "0",
        "codLote": 0,
        "parcela": 0
    },
    {
        "ano": 2026,
        "mes": 2,
        "tipoDespesa": "PASSAGEM AÉREA - SIGEPA",
        "codDocumento": "66A74D32-EA22-4D4A-A302-EE679BC62785",
        "tipoDocumento": "Nota Fiscal",
        "codTipoDocumento": 0,
        "dataDocumento": "2026-02-10T00:00:00",
        "numDocumento": "9572273046821",
        "valorDocumento": -1180.67,
        "urlDocumento": null,
        "nomeFornecedor": "LATAM Airlines Brasil",
        "cnpjCpfFornecedor": "",
        "valorLiquido": -1180.67,
        "valorGlosa": 0.0,
        "numRessarcimento": "0",
        "codLote": 0,
        "parcela": 0
    },
    {
        "ano": 2026,
        "mes": 2,
        "tipoDespesa": "PASSAGEM AÉREA - SIGEPA",
        "codDocumento": "66A74D32-EA22-4D4A-A302-EE679BC62785",
        "tipoDocumento": "Nota Fiscal",
        "codTipoDocumento": 0,
        "dataDocumento": "2026-02-10T00:00:00",
        "numDocumento": "9572273046821",
        "valorDocumento": 1180.67,
        "urlDocumento": null,
        "nomeFornecedor": "LATAM Airlines Brasil",
        "cnpjCpfFornecedor": "",
        "valorLiquido": 1180.67,
        "valorGlosa": 0.0,
        "numRessarcimento": "0",
        "codLote": 0,
        "parcela": 0
    },
    {
        "ano": 2026,
        "mes": 2,
        "tipoDespesa": "PASSAGEM AÉREA - SIGEPA",
        "codDocumento": "E2C345BB-D0E3-4C17-810D-6D1985E8A483",
        "tipoDocumento": "Nota Fiscal",
        "codTipoDocumento": 0,
        "dataDocumento": "2026-02-10T00:00:00",
        "numDocumento": "9572273123745",
        "valorDocumento": 2674.67,
        "urlDocumento": null,
        "nomeFornecedor": "LATAM Airlines Brasil",
        "cnpjCpfFornecedor": "",
        "valorLiquido": 2674.67,
        "valorGlosa": 0.0,
        "numRessarcimento": "0",
        "codLote": 0,
        "parcela": 0
    },
    {
        "ano": 2026,
        "mes": 2,
        "tipoDespesa": "PASSAGEM AÉREA - SIGEPA",
        "codDocumento": "E7C5449C-8A95-4C9E-86D6-7D2F90CA380C",
        "tipoDocumento": "Nota Fiscal",
        "codTipoDocumento": 0,
        "dataDocumento": "2026-02-23T00:00:00",
        "numDocumento": "9572274951813",
        "valorDocumento": 2464.55,
        "urlDocumento": null,
        "nomeFornecedor": "LATAM Airlines Brasil",
        "cnpjCpfFornecedor": "",
        "valorLiquido": 2464.55,
        "valorGlosa": 0.0,
        "numRessarcimento": "0",
        "codLote": 0,
        "parcela": 0
    }
]