[
    {
        "ano": 2026,
        "mes": 1,
        "tipoDespesa": "MANUTENÇÃO DE ESCRITÓRIO DE APOIO À ATIVIDADE PARLAMENTAR",
        "codDocumento": "8046277",
        "tipoDocumento": "Nota Fiscal",
        "codTipoDocumento": 0,
        "dataDocumento": "2026-01-06T00:00:00",
        "numDocumento": "013581811",
        "valorDocumento": 661.31,
        "urlDocumento": "https://www.camara.leg.br/cota-parlamentar/documentos/publ/3637/2026/8046277.pdf",
        "nomeFornecedor": "ENERGISA DISTRIBUIDORA DE ENERGIA / MS.",
        "cnpjCpfFornecedor": "15413826000150",
        "valorLiquido": 645.93,
        "valorGlosa": 15.38,
        "numRessarcimento": "",
        "codLote": 2206573,
        "parcela": 0
    },
    {
        "ano": 2026,
        "mes": 3,
        "tipoDespesa": "MANUTENÇÃO DE ESCRITÓRIO DE APOIO À ATIVIDADE PARLAMENTAR",
        "codDocumento": "8075256",
        "tipoDocumento": "Nota Fiscal",
        "codTipoDocumento": 0,
        "dataDocumento": "2026-03-06T00:00:00",
        "numDocumento": "014683891",
        "valorDocumento": 940.0,
        "urlDocumento": "https://www.camara.leg.br/cota-parlamentar/documentos/publ/3637/2026/8075256.pdf",
        "nomeFornecedor": "ENERGISA DISTRIBUIDORA DE ENERGIA / MS.",
        "cnpjCpfFornecedor": "15413826000150",
        "valorLiquido": 940.0,
        "valorGlosa": 0.0,
        "numRessarcimento": "",
        "codLote": 2222734,
        "parcela": 0
    },
    {
        "ano": 2026,
        "mes": 4,
        "tipoDespesa": "MANUTENÇÃO DE ESCRITÓRIO DE APOIO À ATIVIDADE PARLAMENTAR",
        "codDocumento": "8094850",
        "tipoDocumento": "Nota Fiscal",
        "codTipoDocumento": 0,
        "dataDocumento": "2026-04-06T00:00:00",
        "numDocumento": "015327325",
        "valorDocumento": 1379.02,
        "urlDocumento": "https://www.camara.leg.br/cota-parlamentar/documentos/publ/3637/2026/8094850.pdf",
        "nomeFornecedor": "ENERGISA DISTRIBUIDORA DE ENERGIA / MS.",
        "cnpjCpfFornecedor": "15413826000150",
        "valorLiquido": 1349.3,
        "valorGlosa": 29.72,
        "numRessarcimento": "",
        "codLote": 2233343,
        "parcela": 0
    },
    {
        "ano": 2026,
        "mes": 3,
        "tipoDespesa": "MANUTENÇÃO DE ESCRITÓRIO DE APOIO À ATIVIDADE PARLAMENTAR",
        "codDocumento": "8070289",
        "tipoDocumento": "Nota Fiscal",
        "codTipoDocumento": 0,
        "dataDocumento": "2026-02-04T00:00:00",
        "numDocumento": "14115931",
        "valorDocumento": 1154.52,
        "urlDocumento": "https://www.camara.leg.br/cota-parlamentar/documentos/publ/3637/2026/8070289.pdf",
        "nomeFornecedor": "ENERGISA DISTRIBUIDORA DE ENERGIA / MS.",
        "cnpjCpfFornecedor": "15413826000150",
        "valorLiquido": 1154.52,
        "valorGlosa": 0.0,
        "numRessarcimento": "",
        "codLote": 2220048,
        "parcela": 0
    },
    {
        "ano": 2026,
        "mes": 2,
        "tipoDespesa": "MANUTENÇÃO DE ESCRITÓRIO DE APOIO À ATIVIDADE PARLAMENTAR",
        "codDocumento": "8055046",
        "tipoDocumento": "Recibos/Outros",
        "codTipoDocumento": 1,
        "dataDocumento": "2026-02-24T00:00:00",
        "numDocumento": "05360020136",
        "valorDocumento": 563.35,
        "urlDocumento": "https://www.camara.leg.br/cota-parlamentar/documentos/publ/3637/2026/8055046.pdf",
        "nomeFornecedor": "prefeitura municipal de campo grande",
        "cnpjCpfFornecedor": "03257078000184",
        "valorLiquido": 563.35,
        "valorGlosa": 0.0,
        "numRessarcimento": "",
        "codLote": 2211539,
        "parcela": 0
    },
    {
        "ano": 2026,
        "mes": 2,
        "tipoDespesa": "MANUTENÇÃO DE ESCRITÓRIO DE APOIO À ATIVIDADE PARLAMENTAR",
        "codDocumento": "8055042",
        "tipoDocumento": "Recibos/Outros",
        "codTipoDocumento": 1,
        "dataDocumento": "2026-02-24T00:00:00",
        "numDocumento": "05360020136",
        "valorDocumento": 620.33,
        "urlDocumento": "https://www.camara.leg.br/cota-parlamentar/documentos/publ/3637/2026/8055042.pdf",
        "nomeFornecedor": "prefeitura municipal de campo grande",
        "cnpjCpfFornecedor": "03257078000184",
        "valorLiquido": 620.33,
        "valorGlosa": 0.0,
        "numRessarcimento": "",
        "codLote": 2211539,
        "parcela": 0
    },
    {
        "ano": 2026,
        "mes": 3,
        "tipoDespesa": "MANUTENÇÃO DE ESCRITÓRIO DE APOIO À ATIVIDADE PARLAMENTAR",
        "codDocumento": "8075242",
        "tipoDocumento": "Recibos/Outros",
        "codTipoDocumento": 1,
        "dataDocumento": "2026-04-01T00:00:00",
        "numDocumento": "713409726/2026-3",
        "valorDocumento": 563.35,
        "urlDocumento": "https://www.camara.leg.br/cota-parlamentar/documentos/publ/3637/2026/8075242.pdf",
        "nomeFornecedor": "prefeitura municipal de campo grande",
        "cnpjCpfFornecedor": "03257078000184",
        "valorLiquido": 563.35,
        "valorGlosa": 0.0,
        "numRessarcimento": "",
        "codLote": 2222734,
        "parcela": 0
    },
    {
        "ano": 2026,
        "mes": 4,
        "tipoDespesa": "MANUTENÇÃO DE ESCRITÓRIO DE APOIO À ATIVIDADE PARLAMENTAR",
        "codDocumento": "8094859",
        "tipoDocumento": "Recibos/Outros",
        "codTipoDocumento": 1,
        "dataDocumento": "2026-05-06T00:00:00",
        "numDocumento": "713409826/2026-8",
        "valorDocumento": 563.35,
        "urlDocumento": "https://www.camara.leg.br/cota-parlamentar/documentos/publ/3637/2026/8094859.pdf",
        "nomeFornecedor": "prefeitura municipal de campo grande",
        "cnpjCpfFornecedor": "03257078000184",
        "valorLiquido": 563.35,
        "valorGlosa": 0.0,
        "numRessarcimento": "",
        "codLote": 2233343,
        "parcela": 0
    },
    {
        "ano": 2026,
        "mes": 4,
        "tipoDespesa": "COMBUSTÍVEIS E LUBRIFICANTES.",
        "codDocumento": "8081949",
        "tipoDocumento": "Nota Fiscal Eletrônica",
        "codTipoDocumento": 4,
        "dataDocumento": "2026-04-08T00:00:00",
        "numDocumento": "1719604",
        "valorDocumento": 387.11,
        "urlDocumento": "http://www.camara.leg.br/cota-parlamentar/nota-fiscal-eletronica?ideDocumentoFiscal=8081949",
        "nomeFornecedor": "026 - P WAY - CASCOL COMBUSTIVEIS PARA VEICULOS LTDA",
        "cnpjCpfFornecedor": "00306597002655",
        "valorLiquido": 387.11,
        "valorGlosa": 0.0,
        "numRessarcimento": "",
        "codLote": 2226474,
        "parcela": 0
    },
    {
        "ano": 2026,
        "mes": 3,
        "tipoDespesa": "COMBUSTÍVEIS E LUBRIFICANTES.",
        "codDocumento": "8062553",
        "tipoDocumento": "Nota Fiscal Eletrônica",
        "codTipoDocumento": 4,
        "dataDocumento": "2026-03-06T19:47:51",
        "numDocumento": "566169",
        "valorDocumento": 285.27,
        "urlDocumento": "http://www.camara.leg.br/cota-parlamentar/nota-fiscal-eletronica?ideDocumentoFiscal=8062553",
        "nomeFornecedor": "031 - 302 NORTE - CASCOL COMBUSTIVEIS PARA VEICULOS LTDA",
        "cnpjCpfFornecedor": "00306597003112",
        "valorLiquido": 285.27,
        "valorGlosa": 0.0,
        "numRessarcimento": "",
        "codLote": 2215807,
        "parcela": 0
    },
    {
        "ano": 2026,
        "mes": 4,
        "tipoDespesa": "COMBUSTÍVEIS E LUBRIFICANTES.",
        "codDocumento": "8091185",
        "tipoDocumento": "Nota Fiscal Eletrônica",
        "codTipoDocumento": 4,
        "dataDocumento": "2026-04-29T20:26:50",
        "numDocumento": "729699",
        "valorDocumento": 100.0,
        "urlDocumento": "http://www.camara.leg.br/cota-parlamentar/nota-fiscal-eletronica?ideDocumentoFiscal=8091185",
        "nomeFornecedor": "063 - 311 SUL - CASCOL COMBUSTIVEIS PARA VEICULOS LTDA",
        "cnpjCpfFornecedor": "00306597006308",
        "valorLiquido": 100.0,
        "valorGlosa": 0.0,
        "numRessarcimento": "",
        "codLote": 2231278,
        "parcela": 0
    },
    {
        "ano": 2026,
        "mes": 3,
        "tipoDespesa": "COMBUSTÍVEIS E LUBRIFICANTES.",
        "codDocumento": "8066667",
        "tipoDocumento": "Nota Fiscal Eletrônica",
        "codTipoDocumento": 4,
        "dataDocumento": "2026-03-13T15:46:44",
        "numDocumento": "1361429",
        "valorDocumento": 238.95,
        "urlDocumento": "http://www.camara.leg.br/cota-parlamentar/nota-fiscal-eletronica?ideDocumentoFiscal=8066667",
        "nomeFornecedor": "076 - MELHOR 10 - CASCOL COMBUSTIVEIS PARA VEICULOS LTDA",
        "cnpjCpfFornecedor": "00306597007614",
        "valorLiquido": 238.95,
        "valorGlosa": 0.0,
        "numRessarcimento": "",
        "codLote": 2218120,
        "parcela": 0
    },
    {
        "ano": 2026,
        "mes": 3,
        "tipoDespesa": "COMBUSTÍVEIS E LUBRIFICANTES.",
        "codDocumento": "8068580",
        "tipoDocumento": "Nota Fiscal Eletrônica",
        "codTipoDocumento": 4,
        "dataDocumento": "2026-03-17T22:06:31",
        "numDocumento": "1364293",
        "valorDocumento": 100.0,
        "urlDocumento": "http://www.camara.leg.br/cota-parlamentar/nota-fiscal-eletronica?ideDocumentoFiscal=8068580",
        "nomeFornecedor": "076 - MELHOR 10 - CASCOL COMBUSTIVEIS PARA VEICULOS LTDA",
        "cnpjCpfFornecedor": "00306597007614",
        "valorLiquido": 100.0,
        "valorGlosa": 0.0,
        "numRessarcimento": "",
        "codLote": 2219172,
        "parcela": 0
    },
    {
        "ano": 2026,
        "mes": 4,
        "tipoDespesa": "COMBUSTÍVEIS E LUBRIFICANTES.",
        "codDocumento": "8081582",
        "tipoDocumento": "Nota Fiscal Eletrônica",
        "codTipoDocumento": 4,
        "dataDocumento": "2026-04-13T00:00:00",
        "numDocumento": "1381481",
        "valorDocumento": 200.0,
        "urlDocumento": "http://www.camara.leg.br/cota-parlamentar/nota-fiscal-eletronica?ideDocumentoFiscal=8081582",
        "nomeFornecedor": "076 - MELHOR 10 - CASCOL COMBUSTIVEIS PARA VEICULOS LTDA",
        "cnpjCpfFornecedor": "00306597007614",
        "valorLiquido": 200.0,
        "valorGlosa": 0.0,
        "numRessarcimento": "",
        "codLote": 2226274,
        "parcela": 0
    },
    {
        "ano": 2026,
        "mes": 5,
        "tipoDespesa": "COMBUSTÍVEIS E LUBRIFICANTES.",
        "codDocumento": "8092634",
        "tipoDocumento": "Nota Fiscal Eletrônica",
        "codTipoDocumento": 4,
        "dataDocumento": "2026-05-04T16:48:50",
        "numDocumento": "1394025",
        "valorDocumento": 100.0,
        "urlDocumento": "http://www.camara.leg.br/cota-parlamentar/nota-fiscal-eletronica?ideDocumentoFiscal=8092634",
        "nomeFornecedor": "076 - MELHOR 10 - CASCOL COMBUSTIVEIS PARA VEICULOS LTDA",
        "cnpjCpfFornecedor": "00306597007614",
        "valorLiquido": 100.0,
        "valorGlosa": 0.0,
        "numRessarcimento": "",
        "codLote": 2232062,
        "parcela": 0
    }
]