[
    {
        "ano": 2026,
        "mes": 2,
        "tipoDespesa": "SERVIÇO DE TÁXI, PEDÁGIO E ESTACIONAMENTO",
        "codDocumento": "8057914",
        "tipoDocumento": "Recibos/Outros",
        "codTipoDocumento": 1,
        "dataDocumento": "2026-02-26T00:00:00",
        "numDocumento": "02154",
        "valorDocumento": 8.0,
        "urlDocumento": "https://www.camara.leg.br/cota-parlamentar/documentos/publ/3594/2026/8057914.pdf",
        "nomeFornecedor": "CONC. RODOVIAS DO TIETÊ",
        "cnpjCpfFornecedor": "10678505000163",
        "valorLiquido": 8.0,
        "valorGlosa": 0.0,
        "numRessarcimento": "",
        "codLote": 2213167,
        "parcela": 0
    },
    {
        "ano": 2026,
        "mes": 2,
        "tipoDespesa": "SERVIÇO DE TÁXI, PEDÁGIO E ESTACIONAMENTO",
        "codDocumento": "8071026",
        "tipoDocumento": "Recibos/Outros",
        "codTipoDocumento": 1,
        "dataDocumento": "2026-02-09T00:00:00",
        "numDocumento": "1770658857386",
        "valorDocumento": 405.22,
        "urlDocumento": "https://www.camara.leg.br/cota-parlamentar/documentos/publ/3594/2026/8071026.pdf",
        "nomeFornecedor": "LDS LOCADORA DE VEÍCULOS LTDA",
        "cnpjCpfFornecedor": "51206262000148",
        "valorLiquido": 405.22,
        "valorGlosa": 0.0,
        "numRessarcimento": "",
        "codLote": 2220428,
        "parcela": 0
    },
    {
        "ano": 2026,
        "mes": 2,
        "tipoDespesa": "SERVIÇO DE TÁXI, PEDÁGIO E ESTACIONAMENTO",
        "codDocumento": "8057749",
        "tipoDocumento": "Recibos/Outros",
        "codTipoDocumento": 1,
        "dataDocumento": "2026-02-26T00:00:00",
        "numDocumento": "0211FAQ0Q90",
        "valorDocumento": 13.8,
        "urlDocumento": "https://www.camara.leg.br/cota-parlamentar/documentos/publ/3594/2026/8057749.pdf",
        "nomeFornecedor": "RODOVIA DAS COLINAS S/A",
        "cnpjCpfFornecedor": "03025305000146",
        "valorLiquido": 13.8,
        "valorGlosa": 0.0,
        "numRessarcimento": "",
        "codLote": 2213167,
        "parcela": 0
    },
    {
        "ano": 2026,
        "mes": 2,
        "tipoDespesa": "SERVIÇO DE TÁXI, PEDÁGIO E ESTACIONAMENTO",
        "codDocumento": "8057976",
        "tipoDocumento": "Recibos/Outros",
        "codTipoDocumento": 1,
        "dataDocumento": "2026-02-28T00:00:00",
        "numDocumento": "10908",
        "valorDocumento": 18.8,
        "urlDocumento": "https://www.camara.leg.br/cota-parlamentar/documentos/publ/3594/2026/8057976.pdf",
        "nomeFornecedor": "RODOVIA DAS COLINAS S/A",
        "cnpjCpfFornecedor": "03025305000146",
        "valorLiquido": 18.8,
        "valorGlosa": 0.0,
        "numRessarcimento": "",
        "codLote": 2213168,
        "parcela": 0
    },
    {
        "ano": 2026,
        "mes": 2,
        "tipoDespesa": "PASSAGEM AÉREA - SIGEPA",
        "codDocumento": "587FF597-6834-493D-9A12-909613CF7776",
        "tipoDocumento": "Nota Fiscal",
        "codTipoDocumento": 0,
        "dataDocumento": "2026-02-20T00:00:00",
        "numDocumento": "GI1GKS",
        "valorDocumento": 1516.17,
        "urlDocumento": null,
        "nomeFornecedor": "Azul Linhas Aéreas",
        "cnpjCpfFornecedor": "",
        "valorLiquido": 1516.17,
        "valorGlosa": 0.0,
        "numRessarcimento": "0",
        "codLote": 0,
        "parcela": 0
    },
    {
        "ano": 2026,
        "mes": 4,
        "tipoDespesa": "PASSAGEM AÉREA - SIGEPA",
        "codDocumento": "7E877253-2D98-4E6F-8A14-B9036AF0C15E",
        "tipoDocumento": "Nota Fiscal",
        "codTipoDocumento": 0,
        "dataDocumento": "2026-04-30T00:00:00",
        "numDocumento": "ULQVKZ",
        "valorDocumento": 941.38,
        "urlDocumento": null,
        "nomeFornecedor": "Azul Linhas Aéreas",
        "cnpjCpfFornecedor": "",
        "valorLiquido": 941.38,
        "valorGlosa": 0.0,
        "numRessarcimento": "0",
        "codLote": 0,
        "parcela": 0
    },
    {
        "ano": 2026,
        "mes": 1,
        "tipoDespesa": "PASSAGEM AÉREA - SIGEPA",
        "codDocumento": "4B597145-545F-47B3-8676-6208E28F8EEF",
        "tipoDocumento": "Nota Fiscal",
        "codTipoDocumento": 0,
        "dataDocumento": "2026-01-07T00:00:00",
        "numDocumento": "1272153036633",
        "valorDocumento": 216.89,
        "urlDocumento": null,
        "nomeFornecedor": "Gol Linhas Aéreas",
        "cnpjCpfFornecedor": "",
        "valorLiquido": 216.89,
        "valorGlosa": 0.0,
        "numRessarcimento": "0",
        "codLote": 0,
        "parcela": 0
    },
    {
        "ano": 2026,
        "mes": 2,
        "tipoDespesa": "PASSAGEM AÉREA - SIGEPA",
        "codDocumento": "4B597145-545F-47B3-8676-6208E28F8EEF",
        "tipoDocumento": "Nota Fiscal",
        "codTipoDocumento": 0,
        "dataDocumento": "2026-02-20T00:00:00",
        "numDocumento": "1272153036633",
        "valorDocumento": -62.14,
        "urlDocumento": null,
        "nomeFornecedor": "Gol Linhas Aéreas",
        "cnpjCpfFornecedor": "",
        "valorLiquido": -62.14,
        "valorGlosa": 0.0,
        "numRessarcimento": "0",
        "codLote": 0,
        "parcela": 0
    },
    {
        "ano": 2026,
        "mes": 1,
        "tipoDespesa": "PASSAGEM AÉREA - SIGEPA",
        "codDocumento": "34E8622C-BCC2-424C-B66F-5C991AC6CD81",
        "tipoDocumento": "Nota Fiscal",
        "codTipoDocumento": 0,
        "dataDocumento": "2026-01-07T00:00:00",
        "numDocumento": "1272153037542",
        "valorDocumento": 187.62,
        "urlDocumento": null,
        "nomeFornecedor": "Gol Linhas Aéreas",
        "cnpjCpfFornecedor": "",
        "valorLiquido": 187.62,
        "valorGlosa": 0.0,
        "numRessarcimento": "0",
        "codLote": 0,
        "parcela": 0
    },
    {
        "ano": 2026,
        "mes": 2,
        "tipoDespesa": "PASSAGEM AÉREA - SIGEPA",
        "codDocumento": "86666CD5-D826-425C-BFC6-AEB0863EDBE8",
        "tipoDocumento": "Nota Fiscal",
        "codTipoDocumento": 0,
        "dataDocumento": "2026-02-21T00:00:00",
        "numDocumento": "1272156210549",
        "valorDocumento": 373.64,
        "urlDocumento": null,
        "nomeFornecedor": "Gol Linhas Aéreas",
        "cnpjCpfFornecedor": "",
        "valorLiquido": 373.64,
        "valorGlosa": 0.0,
        "numRessarcimento": "0",
        "codLote": 0,
        "parcela": 0
    },
    {
        "ano": 2026,
        "mes": 3,
        "tipoDespesa": "PASSAGEM AÉREA - SIGEPA",
        "codDocumento": "7222300C-14C8-42FB-A38D-97AEDAEC0EC2",
        "tipoDocumento": "Nota Fiscal",
        "codTipoDocumento": 0,
        "dataDocumento": "2026-03-13T00:00:00",
        "numDocumento": "1272157559955",
        "valorDocumento": 518.99,
        "urlDocumento": null,
        "nomeFornecedor": "Gol Linhas Aéreas",
        "cnpjCpfFornecedor": "",
        "valorLiquido": 518.99,
        "valorGlosa": 0.0,
        "numRessarcimento": "0",
        "codLote": 0,
        "parcela": 0
    },
    {
        "ano": 2026,
        "mes": 4,
        "tipoDespesa": "PASSAGEM AÉREA - SIGEPA",
        "codDocumento": "7222300C-14C8-42FB-A38D-97AEDAEC0EC2",
        "tipoDocumento": "Nota Fiscal",
        "codTipoDocumento": 0,
        "dataDocumento": "2026-04-07T00:00:00",
        "numDocumento": "1272157559955",
        "valorDocumento": -518.99,
        "urlDocumento": null,
        "nomeFornecedor": "Gol Linhas Aéreas",
        "cnpjCpfFornecedor": "",
        "valorLiquido": -518.99,
        "valorGlosa": 0.0,
        "numRessarcimento": "0",
        "codLote": 0,
        "parcela": 0
    },
    {
        "ano": 2026,
        "mes": 3,
        "tipoDespesa": "PASSAGEM AÉREA - SIGEPA",
        "codDocumento": "0F7E9010-2906-4242-84DE-A1D96925C1C9",
        "tipoDocumento": "Nota Fiscal",
        "codTipoDocumento": 0,
        "dataDocumento": "2026-03-17T00:00:00",
        "numDocumento": "1272300048921",
        "valorDocumento": 745.65,
        "urlDocumento": null,
        "nomeFornecedor": "Gol Linhas Aéreas",
        "cnpjCpfFornecedor": "",
        "valorLiquido": 745.65,
        "valorGlosa": 0.0,
        "numRessarcimento": "0",
        "codLote": 0,
        "parcela": 0
    },
    {
        "ano": 2026,
        "mes": 1,
        "tipoDespesa": "PASSAGEM AÉREA - SIGEPA",
        "codDocumento": "810CEBC0-FD09-41C6-B2A0-FA21746D88BF",
        "tipoDocumento": "Nota Fiscal",
        "codTipoDocumento": 0,
        "dataDocumento": "2026-01-05T00:00:00",
        "numDocumento": "9572267207828",
        "valorDocumento": 186.55,
        "urlDocumento": null,
        "nomeFornecedor": "LATAM Airlines Brasil",
        "cnpjCpfFornecedor": "",
        "valorLiquido": 186.55,
        "valorGlosa": 0.0,
        "numRessarcimento": "0",
        "codLote": 0,
        "parcela": 0
    },
    {
        "ano": 2026,
        "mes": 1,
        "tipoDespesa": "PASSAGEM AÉREA - SIGEPA",
        "codDocumento": "5E6C4A74-3E00-4D0D-9E7B-9513A8DFF976",
        "tipoDocumento": "Nota Fiscal",
        "codTipoDocumento": 0,
        "dataDocumento": "2026-01-05T00:00:00",
        "numDocumento": "9572267208561",
        "valorDocumento": 157.28,
        "urlDocumento": null,
        "nomeFornecedor": "LATAM Airlines Brasil",
        "cnpjCpfFornecedor": "",
        "valorLiquido": 157.28,
        "valorGlosa": 0.0,
        "numRessarcimento": "0",
        "codLote": 0,
        "parcela": 0
    }
]